{
	"archive" : {},
	"artifacts" : 
	[
		{
			"path" : "parser/libparser.a"
		}
	],
	"backtrace" : 1,
	"backtraceGraph" : 
	{
		"commands" : 
		[
			"add_library"
		],
		"files" : 
		[
			"parser/CMakeLists.txt"
		],
		"nodes" : 
		[
			{
				"file" : 0
			},
			{
				"command" : 0,
				"file" : 0,
				"line" : 1,
				"parent" : 0
			}
		]
	},
	"compileGroups" : 
	[
		{
			"compileCommandFragments" : 
			[
				{
					"fragment" : "-g  "
				}
			],
			"language" : "C",
			"sourceIndexes" : 
			[
				0
			]
		}
	],
	"id" : "parser::@72798c8d109b1720528b",
	"name" : "parser",
	"nameOnDisk" : "libparser.a",
	"paths" : 
	{
		"build" : "parser",
		"source" : "parser"
	},
	"sourceGroups" : 
	[
		{
			"name" : "Source Files",
			"sourceIndexes" : 
			[
				0
			]
		}
	],
	"sources" : 
	[
		{
			"backtrace" : 1,
			"compileGroupIndex" : 0,
			"path" : "parser/parser.c",
			"sourceGroupIndex" : 0
		}
	],
	"type" : "STATIC_LIBRARY"
}
